library/__init__.py
library/data_processing.py
library/model.py
library/optmization.py
library/train_loop.py
library/utils.py
parse_pytorch-1.10.2.dist-info/METADATA
parse_pytorch-1.10.2.dist-info/WHEEL
parse_pytorch-1.10.2.dist-info/top_level.txt
parse_pytorch-1.10.2.dist-info/RECORD
